magic_admin_flask/__init__.py
magic_admin_flask-0.0.0.0.dist-info/METADATA
magic_admin_flask-0.0.0.0.dist-info/WHEEL
magic_admin_flask-0.0.0.0.dist-info/top_level.txt
magic_admin_flask-0.0.0.0.dist-info/RECORD
